z3scn/__init__.py
z3scn/z3scn.pyd
z3scn/z3scn.pyi
z3scn/zeng64.dll
z3scn-0.2.4.data/data/tests/test_z3scn_api.py
z3scn-0.2.4.dist-info/licenses/LICENSE
z3scn-0.2.4.dist-info/METADATA
z3scn-0.2.4.dist-info/WHEEL
z3scn-0.2.4.dist-info/top_level.txt
z3scn-0.2.4.dist-info/RECORD
