Metadata-Version: 2.4
Name: z3scn
Version: 0.2.4
Summary: Full version of zCube Developer Kit for Dyadic System SCN5 and SCN6 Actuators
Home-page: https://www.eksimracing.org/zcube-developer-kit
Author: Zappadoc
Author-email: support@eksimracing.org
License: EULA
Project-URL: Homepage, https://www.eksimracing.org/zcube-developer-kit/
Project-URL: Documentation, https://zappadoc.com/dev-support/zcube-developer-kit-for-python/
Project-URL: License, https://www.eksimracing.org/terms-conditions/
Keywords: zcube full commercial eula developer kit
Classifier: Development Status :: 5 - Production/Stable
Classifier: Operating System :: Microsoft :: Windows
Classifier: Topic :: Software Development :: Libraries
Classifier: Topic :: Education
Classifier: Topic :: Games/Entertainment
Classifier: Topic :: Scientific/Engineering
Classifier: Intended Audience :: Developers
Classifier: Intended Audience :: Science/Research
Classifier: Intended Audience :: End Users/Desktop
Classifier: License :: Other/Proprietary License
Classifier: Programming Language :: Python :: 3 :: Only
Classifier: Programming Language :: Python :: 3.8
Classifier: Programming Language :: Python :: 3.9
Classifier: Programming Language :: Python :: 3.10
Classifier: Programming Language :: Python :: 3.11
Classifier: Programming Language :: Python :: 3.12
Requires-Python: >=3.8
License-File: LICENSE
Dynamic: author
Dynamic: author-email
Dynamic: classifier
Dynamic: description
Dynamic: description-content-type
Dynamic: home-page
Dynamic: keywords
Dynamic: license
Dynamic: license-file
Dynamic: project-url
Dynamic: requires-python
Dynamic: summary
